{"Compiler":"2","ProjectWatches":"{\"Value\":[]}","ProjectBreakpoints":"{\"CodeBreakpoints\":{},\"Value\":{}}","OpenedDocuments":"[{\"DocumentPath\":\"04_read_db_to_excel.xaml\",\"FactoryId\":\"{ACB8E7BA-F093-44C1-9B50-33ECA51AAE16}\"},{\"DocumentPath\":\"05_email.xaml\",\"FactoryId\":\"{ACB8E7BA-F093-44C1-9B50-33ECA51AAE16}\"},{\"DocumentPath\":\"01_get_pdf.xaml\",\"FactoryId\":\"{ACB8E7BA-F093-44C1-9B50-33ECA51AAE16}\"},{\"DocumentPath\":\"02_read_pdf.xaml\",\"FactoryId\":\"{ACB8E7BA-F093-44C1-9B50-33ECA51AAE16}\"},{\"DocumentPath\":\"Main.xaml\",\"FactoryId\":\"{ACB8E7BA-F093-44C1-9B50-33ECA51AAE16}\"},{\"DocumentPath\":\"03_write_db.xaml\",\"FactoryId\":\"{ACB8E7BA-F093-44C1-9B50-33ECA51AAE16}\"}]","ProjectActivitiesViewState":"{\"02_read_pdf.xaml\":[{\"ActivityIdRef\":\"GenerateChatCompletion_1\",\"IsAdvancedOptionsExpanded\":false,\"Categories\":{\"Optionen\":true,\"Ausgabe\":true},\"Widgets\":{}},{\"ActivityIdRef\":\"LogMessage_1\",\"IsAdvancedOptionsExpanded\":false,\"Widgets\":{}},{\"ActivityIdRef\":\"Throw_1\",\"IsAdvancedOptionsExpanded\":false,\"Widgets\":{}},{\"ActivityIdRef\":\"If_2\",\"IsAdvancedOptionsExpanded\":false,\"Widgets\":{\"Then\":{\"ShowExpanded\":true},\"Else\":{\"ShowExpanded\":false}}},{\"ActivityIdRef\":\"ExtractPDFText_1\",\"IsAdvancedOptionsExpanded\":false,\"Categories\":{\"Erweiterte Optionen\":true,\"Ausgabe\":true},\"Widgets\":{}},{\"ActivityIdRef\":\"ExtractPDFText_2\",\"IsAdvancedOptionsExpanded\":false,\"Categories\":{\"Erweiterte Optionen\":true,\"Ausgabe\":true},\"Widgets\":{}},{\"ActivityIdRef\":\"LogMessage_2\",\"IsAdvancedOptionsExpanded\":false,\"Widgets\":{}},{\"ActivityIdRef\":\"Throw_4\",\"IsAdvancedOptionsExpanded\":false,\"Widgets\":{}}],\"Main.xaml\":[{\"ActivityIdRef\":\"ForEach`1_1\",\"IsAdvancedOptionsExpanded\":false,\"Categories\":{\"\":true},\"Widgets\":{\"Body\":{\"ShowExpanded\":true}}}],\"01_get_pdf.xaml\":[{\"ActivityIdRef\":\"If_2\",\"IsAdvancedOptionsExpanded\":false,\"Widgets\":{\"Then\":{\"ShowExpanded\":true},\"Else\":{\"ShowExpanded\":false}}},{\"ActivityIdRef\":\"If_5\",\"IsAdvancedOptionsExpanded\":false,\"Widgets\":{\"Then\":{\"ShowExpanded\":true},\"Else\":{\"ShowExpanded\":false}}},{\"ActivityIdRef\":\"If_4\",\"IsAdvancedOptionsExpanded\":false,\"Widgets\":{\"Then\":{\"ShowExpanded\":true},\"Else\":{\"ShowExpanded\":false}}},{\"ActivityIdRef\":\"If_3\",\"IsAdvancedOptionsExpanded\":false,\"Widgets\":{\"Then\":{\"ShowExpanded\":true},\"Else\":{\"ShowExpanded\":false}}},{\"ActivityIdRef\":\"ForEach`1_1\",\"IsAdvancedOptionsExpanded\":false,\"Categories\":{\"\":true},\"Widgets\":{\"Body\":{\"ShowExpanded\":true}}},{\"ActivityIdRef\":\"If_6\",\"IsAdvancedOptionsExpanded\":false,\"Widgets\":{\"Then\":{\"ShowExpanded\":true},\"Else\":{\"ShowExpanded\":false}}},{\"ActivityIdRef\":\"DownloadFileFromUrl_1\",\"IsAdvancedOptionsExpanded\":false,\"Categories\":{\"Optionen\":true,\"Ausgabe\":true},\"Widgets\":{}},{\"ActivityIdRef\":\"ForEach`1_2\",\"IsAdvancedOptionsExpanded\":false,\"Categories\":{\"\":true},\"Widgets\":{\"Body\":{\"ShowExpanded\":true}}},{\"ActivityIdRef\":\"If_7\",\"IsAdvancedOptionsExpanded\":false,\"Widgets\":{\"Then\":{\"ShowExpanded\":true},\"Else\":{\"ShowExpanded\":false}}},{\"ActivityIdRef\":\"DownloadFileFromUrl_2\",\"IsAdvancedOptionsExpanded\":false,\"Categories\":{\"Optionen\":true,\"Ausgabe\":true},\"Widgets\":{}}],\"02_read_pdf_old.xaml\":[{\"ActivityIdRef\":\"ExtractPDFText_1\",\"IsAdvancedOptionsExpanded\":false,\"Categories\":{\"Erweiterte Optionen\":true,\"Ausgabe\":true},\"Widgets\":{}},{\"ActivityIdRef\":\"GenerateChatCompletion_1\",\"IsAdvancedOptionsExpanded\":false,\"Categories\":{\"Optionen\":true,\"Ausgabe\":true},\"Widgets\":{}},{\"ActivityIdRef\":\"If_1\",\"IsAdvancedOptionsExpanded\":false,\"Widgets\":{\"Then\":{\"ShowExpanded\":true},\"Else\":{\"ShowExpanded\":false}}},{\"ActivityIdRef\":\"Throw_2\",\"IsAdvancedOptionsExpanded\":false,\"Widgets\":{}},{\"ActivityIdRef\":\"LogMessage_1\",\"IsAdvancedOptionsExpanded\":false,\"Widgets\":{}},{\"ActivityIdRef\":\"Throw_3\",\"IsAdvancedOptionsExpanded\":false,\"Widgets\":{}},{\"ActivityIdRef\":\"WriteLine_1\",\"IsAdvancedOptionsExpanded\":false,\"Widgets\":{}},{\"ActivityIdRef\":\"ExtractPDFText_4\",\"IsAdvancedOptionsExpanded\":false,\"Categories\":{\"Erweiterte Optionen\":true,\"Ausgabe\":true},\"Widgets\":{}},{\"ActivityIdRef\":\"ForEach`1_3\",\"IsAdvancedOptionsExpanded\":false,\"Categories\":{\"\":true},\"Widgets\":{\"Body\":{\"ShowExpanded\":true}}},{\"ActivityIdRef\":\"ExtractPDFText_5\",\"IsAdvancedOptionsExpanded\":false,\"Categories\":{\"Erweiterte Optionen\":true,\"Ausgabe\":true},\"Widgets\":{}}],\"03_write_db.xaml\":[{\"ActivityIdRef\":\"ListDatabases_1\",\"IsAdvancedOptionsExpanded\":false,\"Widgets\":{}},{\"ActivityIdRef\":\"MongoDBApplicationScope_1\",\"IsAdvancedOptionsExpanded\":false,\"Widgets\":{}},{\"ActivityIdRef\":\"If_1\",\"IsAdvancedOptionsExpanded\":false,\"Widgets\":{\"Then\":{\"ShowExpanded\":true},\"Else\":{\"ShowExpanded\":false}}},{\"ActivityIdRef\":\"LogMessage_1\",\"IsAdvancedOptionsExpanded\":false,\"Widgets\":{}},{\"ActivityIdRef\":\"Throw_1\",\"IsAdvancedOptionsExpanded\":false,\"Widgets\":{}},{\"ActivityIdRef\":\"If_2\",\"IsAdvancedOptionsExpanded\":false,\"Widgets\":{\"Then\":{\"ShowExpanded\":true},\"Else\":{\"ShowExpanded\":false}}},{\"ActivityIdRef\":\"ListCollections_1\",\"IsAdvancedOptionsExpanded\":false,\"Widgets\":{}},{\"ActivityIdRef\":\"CreateCollection_1\",\"IsAdvancedOptionsExpanded\":false,\"Widgets\":{}},{\"ActivityIdRef\":\"Insert_1\",\"IsAdvancedOptionsExpanded\":false,\"Widgets\":{}},{\"ActivityIdRef\":\"Find_1\",\"IsAdvancedOptionsExpanded\":false,\"Widgets\":{}}]}"}